{"version":22,"encryptionVariant":"None","name":"BeaconBeam","hasParentName":false,"samplerDefinitionMap":{"BeaconTexture":{"reg":0,"access":"Read","precision":0,"allowUnorderedAccess":false,"type":"Type2D","textureFormat":"","unknownInt":1,"unknownByte":0,"hasDefaultTexture":false,"hasCustomTypeInfo":false}},"propertyFieldMap":{"UVAnimation":{"num":1,"type":2,"hasData":true,"vectorData":[0.0,0.0,0.0,0.0]},"TileLightColor":{"num":1,"type":2,"hasData":true,"vectorData":[0.0,0.0,0.0,0.0]},"FogAndDistanceControl":{"num":1,"type":2,"hasData":true,"vectorData":[0.0,0.0,0.0,0.0]},"OverlayColor":{"num":1,"type":2,"hasData":true,"vectorData":[0.0,0.0,0.0,0.0]},"FogColor":{"num":1,"type":2,"hasData":true,"vectorData":[1.0,1.0,1.0,1.0]},"SubPixelOffset":{"num":1,"type":2,"hasData":true,"vectorData":[0.0,0.0,0.0,0.0]}},"formatVersion":"V1","dataOnly":true,"passMap":{"Transparent":{"bitSet":"1111111111111111","fallback":"","hasDefaultBlendMode":false,"flagDefaultValues":{"Fancy":"On"},"variantList":[{"isSupported":true,"flags":{"Fancy":"Off"},"shaderCodes":[{"platformShaderStage":{"stageName":"Vertex","platformName":"Metal","stage":"Vertex","platform":"Metal"},"shaderCode":{"shaderInputMap":{"color":{"type":"Vec4","attribute":"Color0","isPerInstance":false,"hasPrecisionConstraint":false,"hasInterpolationConstraint":false},"normal":{"type":"Vec4","attribute":"Normal","isPerInstance":false,"hasPrecisionConstraint":false,"hasInterpolationConstraint":false},"position":{"type":"Vec3","attribute":"Position","isPerInstance":false,"hasPrecisionConstraint":false,"hasInterpolationConstraint":false},"texCoords":{"type":"Vec2","attribute":"TexCoord0","isPerInstance":false,"hasPrecisionConstraint":false,"hasInterpolationConstraint":false}},"sourceHash":4550783349755469196}},{"platformShaderStage":{"stageName":"Fragment","platformName":"Metal","stage":"Fragment","platform":"Metal"},"shaderCode":{"shaderInputMap":{"color":{"type":"Vec4","attribute":"Color0","isPerInstance":false,"hasPrecisionConstraint":false,"hasInterpolationConstraint":false},"fog":{"type":"Vec4","attribute":"Color2","isPerInstance":false,"hasPrecisionConstraint":false,"hasInterpolationConstraint":false},"light":{"type":"Vec4","attribute":"Color1","isPerInstance":false,"hasPrecisionConstraint":false,"hasInterpolationConstraint":false},"texCoords":{"type":"Vec2","attribute":"TexCoord0","isPerInstance":false,"hasPrecisionConstraint":false,"hasInterpolationConstraint":false}},"sourceHash":6583856009554026771}}]},{"isSupported":true,"flags":{"Fancy":"On"},"shaderCodes":[{"platformShaderStage":{"stageName":"Vertex","platformName":"Metal","stage":"Vertex","platform":"Metal"},"shaderCode":{"shaderInputMap":{"color":{"type":"Vec4","attribute":"Color0","isPerInstance":false,"hasPrecisionConstraint":false,"hasInterpolationConstraint":false},"normal":{"type":"Vec4","attribute":"Normal","isPerInstance":false,"hasPrecisionConstraint":false,"hasInterpolationConstraint":false},"position":{"type":"Vec3","attribute":"Position","isPerInstance":false,"hasPrecisionConstraint":false,"hasInterpolationConstraint":false},"texCoords":{"type":"Vec2","attribute":"TexCoord0","isPerInstance":false,"hasPrecisionConstraint":false,"hasInterpolationConstraint":false}},"sourceHash":6321458263504455055}},{"platformShaderStage":{"stageName":"Fragment","platformName":"Metal","stage":"Fragment","platform":"Metal"},"shaderCode":{"shaderInputMap":{"color":{"type":"Vec4","attribute":"Color0","isPerInstance":false,"hasPrecisionConstraint":false,"hasInterpolationConstraint":false},"fog":{"type":"Vec4","attribute":"Color2","isPerInstance":false,"hasPrecisionConstraint":false,"hasInterpolationConstraint":false},"light":{"type":"Vec4","attribute":"Color1","isPerInstance":false,"hasPrecisionConstraint":false,"hasInterpolationConstraint":false},"texCoords":{"type":"Vec2","attribute":"TexCoord0","isPerInstance":false,"hasPrecisionConstraint":false,"hasInterpolationConstraint":false}},"sourceHash":-3552342308595411999}}]}]},"Opaque":{"bitSet":"1111111111111111","fallback":"","hasDefaultBlendMode":false,"flagDefaultValues":{"Fancy":"On"},"variantList":[{"isSupported":true,"flags":{"Fancy":"Off"},"shaderCodes":[{"platformShaderStage":{"stageName":"Vertex","platformName":"Metal","stage":"Vertex","platform":"Metal"},"shaderCode":{"shaderInputMap":{"color":{"type":"Vec4","attribute":"Color0","isPerInstance":false,"hasPrecisionConstraint":false,"hasInterpolationConstraint":false},"normal":{"type":"Vec4","attribute":"Normal","isPerInstance":false,"hasPrecisionConstraint":false,"hasInterpolationConstraint":false},"position":{"type":"Vec3","attribute":"Position","isPerInstance":false,"hasPrecisionConstraint":false,"hasInterpolationConstraint":false},"texCoords":{"type":"Vec2","attribute":"TexCoord0","isPerInstance":false,"hasPrecisionConstraint":false,"hasInterpolationConstraint":false}},"sourceHash":1855797682163878449}},{"platformShaderStage":{"stageName":"Fragment","platformName":"Metal","stage":"Fragment","platform":"Metal"},"shaderCode":{"shaderInputMap":{"color":{"type":"Vec4","attribute":"Color0","isPerInstance":false,"hasPrecisionConstraint":false,"hasInterpolationConstraint":false},"fog":{"type":"Vec4","attribute":"Color2","isPerInstance":false,"hasPrecisionConstraint":false,"hasInterpolationConstraint":false},"light":{"type":"Vec4","attribute":"Color1","isPerInstance":false,"hasPrecisionConstraint":false,"hasInterpolationConstraint":false},"texCoords":{"type":"Vec2","attribute":"TexCoord0","isPerInstance":false,"hasPrecisionConstraint":false,"hasInterpolationConstraint":false}},"sourceHash":-2144846347950467317}}]},{"isSupported":true,"flags":{"Fancy":"On"},"shaderCodes":[{"platformShaderStage":{"stageName":"Vertex","platformName":"Metal","stage":"Vertex","platform":"Metal"},"shaderCode":{"shaderInputMap":{"color":{"type":"Vec4","attribute":"Color0","isPerInstance":false,"hasPrecisionConstraint":false,"hasInterpolationConstraint":false},"normal":{"type":"Vec4","attribute":"Normal","isPerInstance":false,"hasPrecisionConstraint":false,"hasInterpolationConstraint":false},"position":{"type":"Vec3","attribute":"Position","isPerInstance":false,"hasPrecisionConstraint":false,"hasInterpolationConstraint":false},"texCoords":{"type":"Vec2","attribute":"TexCoord0","isPerInstance":false,"hasPrecisionConstraint":false,"hasInterpolationConstraint":false}},"sourceHash":-5947159165251085130}},{"platformShaderStage":{"stageName":"Fragment","platformName":"Metal","stage":"Fragment","platform":"Metal"},"shaderCode":{"shaderInputMap":{"color":{"type":"Vec4","attribute":"Color0","isPerInstance":false,"hasPrecisionConstraint":false,"hasInterpolationConstraint":false},"fog":{"type":"Vec4","attribute":"Color2","isPerInstance":false,"hasPrecisionConstraint":false,"hasInterpolationConstraint":false},"light":{"type":"Vec4","attribute":"Color1","isPerInstance":false,"hasPrecisionConstraint":false,"hasInterpolationConstraint":false},"texCoords":{"type":"Vec2","attribute":"TexCoord0","isPerInstance":false,"hasPrecisionConstraint":false,"hasInterpolationConstraint":false}},"sourceHash":-3595050122717716668}}]}]}}}