{
  "version": 22,
  "encryptionVariant": "None",
  "name": "EditorBlockVolumeHull",
  "hasParentName": false,
  "samplerDefinitionMap": {},
  "propertyFieldMap": {
    "CameraDirection": {
      "num": 1,
      "type": 2,
      "hasData": true,
      "vectorData": [
        1.0,
        0.0,
        0.0,
        1.0
      ]
    },
    "MatColor": {
      "num": 1,
      "type": 2,
      "hasData": true,
      "vectorData": [
        1.0,
        1.0,
        0.0,
        1.0
      ]
    }
  },
  "dataOnly": true,
  "passMap": {
    "Opaque": {
      "bitSet": "111111111111111",
      "fallback": "",
      "hasDefaultBlendMode": false,
      "flagDefaultValues": {},
      "variantList": [
        {
          "isSupported": true,
          "flags": {},
          "shaderCodes": [
            {
              "platformShaderStage": {
                "stageName": "Vertex",
                "platformName": "Direct3D_SM40",
                "stage": "Vertex",
                "platform": "Direct3D_SM40"
              },
              "shaderCode": {
                "shaderInputMap": {
                  "position": {
                    "type": "Vec3",
                    "attribute": "Position",
                    "isPerInstance": false,
                    "hasPrecisionConstraint": false,
                    "hasInterpolationConstraint": false
                  },
                  "normal": {
                    "type": "Vec3",
                    "attribute": "Normal",
                    "isPerInstance": false,
                    "hasPrecisionConstraint": false,
                    "hasInterpolationConstraint": false
                  },
                  "texcoord0": {
                    "type": "Vec2",
                    "attribute": "TexCoord0",
                    "isPerInstance": false,
                    "hasPrecisionConstraint": false,
                    "hasInterpolationConstraint": false
                  }
                },
                "sourceHash": 2612343014680891984
              }
            },
            {
              "platformShaderStage": {
                "stageName": "Fragment",
                "platformName": "Direct3D_SM50",
                "stage": "Fragment",
                "platform": "Direct3D_SM50"
              },
              "shaderCode": {
                "shaderInputMap": {
                  "texcoord0": {
                    "type": "Vec2",
                    "attribute": "TexCoord0",
                    "isPerInstance": false,
                    "hasPrecisionConstraint": false,
                    "hasInterpolationConstraint": false
                  },
                  "normal": {
                    "type": "Vec3",
                    "attribute": "Normal",
                    "isPerInstance": false,
                    "hasPrecisionConstraint": false,
                    "hasInterpolationConstraint": false
                  }
                },
                "sourceHash": 3526098366876612975
              }
            },
            {
              "platformShaderStage": {
                "stageName": "Fragment",
                "platformName": "Direct3D_SM40",
                "stage": "Fragment",
                "platform": "Direct3D_SM40"
              },
              "shaderCode": {
                "shaderInputMap": {
                  "texcoord0": {
                    "type": "Vec2",
                    "attribute": "TexCoord0",
                    "isPerInstance": false,
                    "hasPrecisionConstraint": false,
                    "hasInterpolationConstraint": false
                  },
                  "normal": {
                    "type": "Vec3",
                    "attribute": "Normal",
                    "isPerInstance": false,
                    "hasPrecisionConstraint": false,
                    "hasInterpolationConstraint": false
                  }
                },
                "sourceHash": -4648016987076815064
              }
            },
            {
              "platformShaderStage": {
                "stageName": "Vertex",
                "platformName": "Direct3D_SM50",
                "stage": "Vertex",
                "platform": "Direct3D_SM50"
              },
              "shaderCode": {
                "shaderInputMap": {
                  "position": {
                    "type": "Vec3",
                    "attribute": "Position",
                    "isPerInstance": false,
                    "hasPrecisionConstraint": false,
                    "hasInterpolationConstraint": false
                  },
                  "normal": {
                    "type": "Vec3",
                    "attribute": "Normal",
                    "isPerInstance": false,
                    "hasPrecisionConstraint": false,
                    "hasInterpolationConstraint": false
                  },
                  "texcoord0": {
                    "type": "Vec2",
                    "attribute": "TexCoord0",
                    "isPerInstance": false,
                    "hasPrecisionConstraint": false,
                    "hasInterpolationConstraint": false
                  }
                },
                "sourceHash": -4505376607562270537
              }
            },
            {
              "platformShaderStage": {
                "stageName": "Vertex",
                "platformName": "Direct3D_SM60",
                "stage": "Vertex",
                "platform": "Direct3D_SM60"
              },
              "shaderCode": {
                "shaderInputMap": {
                  "position": {
                    "type": "Vec3",
                    "attribute": "Position",
                    "isPerInstance": false,
                    "hasPrecisionConstraint": false,
                    "hasInterpolationConstraint": false
                  },
                  "normal": {
                    "type": "Vec3",
                    "attribute": "Normal",
                    "isPerInstance": false,
                    "hasPrecisionConstraint": false,
                    "hasInterpolationConstraint": false
                  },
                  "texcoord0": {
                    "type": "Vec2",
                    "attribute": "TexCoord0",
                    "isPerInstance": false,
                    "hasPrecisionConstraint": false,
                    "hasInterpolationConstraint": false
                  }
                },
                "sourceHash": -5848986032289450477
              }
            },
            {
              "platformShaderStage": {
                "stageName": "Fragment",
                "platformName": "Direct3D_SM65",
                "stage": "Fragment",
                "platform": "Direct3D_SM65"
              },
              "shaderCode": {
                "shaderInputMap": {
                  "texcoord0": {
                    "type": "Vec2",
                    "attribute": "TexCoord0",
                    "isPerInstance": false,
                    "hasPrecisionConstraint": false,
                    "hasInterpolationConstraint": false
                  },
                  "normal": {
                    "type": "Vec3",
                    "attribute": "Normal",
                    "isPerInstance": false,
                    "hasPrecisionConstraint": false,
                    "hasInterpolationConstraint": false
                  }
                },
                "sourceHash": 614217805878836229
              }
            },
            {
              "platformShaderStage": {
                "stageName": "Fragment",
                "platformName": "Direct3D_SM60",
                "stage": "Fragment",
                "platform": "Direct3D_SM60"
              },
              "shaderCode": {
                "shaderInputMap": {
                  "texcoord0": {
                    "type": "Vec2",
                    "attribute": "TexCoord0",
                    "isPerInstance": false,
                    "hasPrecisionConstraint": false,
                    "hasInterpolationConstraint": false
                  },
                  "normal": {
                    "type": "Vec3",
                    "attribute": "Normal",
                    "isPerInstance": false,
                    "hasPrecisionConstraint": false,
                    "hasInterpolationConstraint": false
                  }
                },
                "sourceHash": -4811394987916679315
              }
            },
            {
              "platformShaderStage": {
                "stageName": "Vertex",
                "platformName": "Direct3D_SM65",
                "stage": "Vertex",
                "platform": "Direct3D_SM65"
              },
              "shaderCode": {
                "shaderInputMap": {
                  "position": {
                    "type": "Vec3",
                    "attribute": "Position",
                    "isPerInstance": false,
                    "hasPrecisionConstraint": false,
                    "hasInterpolationConstraint": false
                  },
                  "normal": {
                    "type": "Vec3",
                    "attribute": "Normal",
                    "isPerInstance": false,
                    "hasPrecisionConstraint": false,
                    "hasInterpolationConstraint": false
                  },
                  "texcoord0": {
                    "type": "Vec2",
                    "attribute": "TexCoord0",
                    "isPerInstance": false,
                    "hasPrecisionConstraint": false,
                    "hasInterpolationConstraint": false
                  }
                },
                "sourceHash": 3006662010913400784
              }
            }
          ]
        }
      ]
    },
    "Transparent": {
      "bitSet": "111111111111111",
      "fallback": "",
      "hasDefaultBlendMode": false,
      "flagDefaultValues": {},
      "variantList": [
        {
          "isSupported": true,
          "flags": {},
          "shaderCodes": [
            {
              "platformShaderStage": {
                "stageName": "Vertex",
                "platformName": "Direct3D_SM40",
                "stage": "Vertex",
                "platform": "Direct3D_SM40"
              },
              "shaderCode": {
                "shaderInputMap": {
                  "position": {
                    "type": "Vec3",
                    "attribute": "Position",
                    "isPerInstance": false,
                    "hasPrecisionConstraint": false,
                    "hasInterpolationConstraint": false
                  },
                  "normal": {
                    "type": "Vec3",
                    "attribute": "Normal",
                    "isPerInstance": false,
                    "hasPrecisionConstraint": false,
                    "hasInterpolationConstraint": false
                  },
                  "texcoord0": {
                    "type": "Vec2",
                    "attribute": "TexCoord0",
                    "isPerInstance": false,
                    "hasPrecisionConstraint": false,
                    "hasInterpolationConstraint": false
                  }
                },
                "sourceHash": -5247918604724422635
              }
            },
            {
              "platformShaderStage": {
                "stageName": "Fragment",
                "platformName": "Direct3D_SM50",
                "stage": "Fragment",
                "platform": "Direct3D_SM50"
              },
              "shaderCode": {
                "shaderInputMap": {
                  "texcoord0": {
                    "type": "Vec2",
                    "attribute": "TexCoord0",
                    "isPerInstance": false,
                    "hasPrecisionConstraint": false,
                    "hasInterpolationConstraint": false
                  },
                  "normal": {
                    "type": "Vec3",
                    "attribute": "Normal",
                    "isPerInstance": false,
                    "hasPrecisionConstraint": false,
                    "hasInterpolationConstraint": false
                  }
                },
                "sourceHash": 3591065978131896998
              }
            },
            {
              "platformShaderStage": {
                "stageName": "Fragment",
                "platformName": "Direct3D_SM40",
                "stage": "Fragment",
                "platform": "Direct3D_SM40"
              },
              "shaderCode": {
                "shaderInputMap": {
                  "texcoord0": {
                    "type": "Vec2",
                    "attribute": "TexCoord0",
                    "isPerInstance": false,
                    "hasPrecisionConstraint": false,
                    "hasInterpolationConstraint": false
                  },
                  "normal": {
                    "type": "Vec3",
                    "attribute": "Normal",
                    "isPerInstance": false,
                    "hasPrecisionConstraint": false,
                    "hasInterpolationConstraint": false
                  }
                },
                "sourceHash": 4901009609895661384
              }
            },
            {
              "platformShaderStage": {
                "stageName": "Vertex",
                "platformName": "Direct3D_SM50",
                "stage": "Vertex",
                "platform": "Direct3D_SM50"
              },
              "shaderCode": {
                "shaderInputMap": {
                  "position": {
                    "type": "Vec3",
                    "attribute": "Position",
                    "isPerInstance": false,
                    "hasPrecisionConstraint": false,
                    "hasInterpolationConstraint": false
                  },
                  "normal": {
                    "type": "Vec3",
                    "attribute": "Normal",
                    "isPerInstance": false,
                    "hasPrecisionConstraint": false,
                    "hasInterpolationConstraint": false
                  },
                  "texcoord0": {
                    "type": "Vec2",
                    "attribute": "TexCoord0",
                    "isPerInstance": false,
                    "hasPrecisionConstraint": false,
                    "hasInterpolationConstraint": false
                  }
                },
                "sourceHash": -8033431429901042098
              }
            },
            {
              "platformShaderStage": {
                "stageName": "Vertex",
                "platformName": "Direct3D_SM60",
                "stage": "Vertex",
                "platform": "Direct3D_SM60"
              },
              "shaderCode": {
                "shaderInputMap": {
                  "position": {
                    "type": "Vec3",
                    "attribute": "Position",
                    "isPerInstance": false,
                    "hasPrecisionConstraint": false,
                    "hasInterpolationConstraint": false
                  },
                  "normal": {
                    "type": "Vec3",
                    "attribute": "Normal",
                    "isPerInstance": false,
                    "hasPrecisionConstraint": false,
                    "hasInterpolationConstraint": false
                  },
                  "texcoord0": {
                    "type": "Vec2",
                    "attribute": "TexCoord0",
                    "isPerInstance": false,
                    "hasPrecisionConstraint": false,
                    "hasInterpolationConstraint": false
                  }
                },
                "sourceHash": -1923428971763705209
              }
            },
            {
              "platformShaderStage": {
                "stageName": "Fragment",
                "platformName": "Direct3D_SM65",
                "stage": "Fragment",
                "platform": "Direct3D_SM65"
              },
              "shaderCode": {
                "shaderInputMap": {
                  "texcoord0": {
                    "type": "Vec2",
                    "attribute": "TexCoord0",
                    "isPerInstance": false,
                    "hasPrecisionConstraint": false,
                    "hasInterpolationConstraint": false
                  },
                  "normal": {
                    "type": "Vec3",
                    "attribute": "Normal",
                    "isPerInstance": false,
                    "hasPrecisionConstraint": false,
                    "hasInterpolationConstraint": false
                  }
                },
                "sourceHash": -443564625841424412
              }
            },
            {
              "platformShaderStage": {
                "stageName": "Fragment",
                "platformName": "Direct3D_SM60",
                "stage": "Fragment",
                "platform": "Direct3D_SM60"
              },
              "shaderCode": {
                "shaderInputMap": {
                  "texcoord0": {
                    "type": "Vec2",
                    "attribute": "TexCoord0",
                    "isPerInstance": false,
                    "hasPrecisionConstraint": false,
                    "hasInterpolationConstraint": false
                  },
                  "normal": {
                    "type": "Vec3",
                    "attribute": "Normal",
                    "isPerInstance": false,
                    "hasPrecisionConstraint": false,
                    "hasInterpolationConstraint": false
                  }
                },
                "sourceHash": 1641580712451740695
              }
            },
            {
              "platformShaderStage": {
                "stageName": "Vertex",
                "platformName": "Direct3D_SM65",
                "stage": "Vertex",
                "platform": "Direct3D_SM65"
              },
              "shaderCode": {
                "shaderInputMap": {
                  "position": {
                    "type": "Vec3",
                    "attribute": "Position",
                    "isPerInstance": false,
                    "hasPrecisionConstraint": false,
                    "hasInterpolationConstraint": false
                  },
                  "normal": {
                    "type": "Vec3",
                    "attribute": "Normal",
                    "isPerInstance": false,
                    "hasPrecisionConstraint": false,
                    "hasInterpolationConstraint": false
                  },
                  "texcoord0": {
                    "type": "Vec2",
                    "attribute": "TexCoord0",
                    "isPerInstance": false,
                    "hasPrecisionConstraint": false,
                    "hasInterpolationConstraint": false
                  }
                },
                "sourceHash": 7524104648482744723
              }
            }
          ]
        }
      ]
    }
  }
}